{
  "$id": "https://raw.githubusercontent.com/dargolith/iotdatamodel/master/src/associations/HasConfig.json",
  "title": "HasConfig",
  "description": "An entity linking a Config to another entity",
  "type": "object",
  "meta": {
    "orientdb": {
      "super": "E",
      "uniqueEdge": true,
      "uniqueIdEdge": true
    }
  },
  "required": ["rid", "id"],
  "properties": {
    "rid": {
      "description": "The record id of the HasConfig link",
      "type": "string"
    },
    "id": {
      "description": "The custom id of the linked Config for an entity",
      "type": "string"
    }
  }
}
